[

	{
		"name": "Nut",
		"replaces": "Farm",
		"uniqueTo": "Opawa",
		"terrainsCanBeBuiltOn": ["Plains","Grassland","Desert","Flood plains"],
		"food": 1,
		"turnsToBuild": 7,
		"techRequired": "Agriculture",
		"uniques": ["Can also be built on tiles adjacent to fresh water", 
			"[+1 Food] on [Fresh water] tiles once [Civil Service] is discovered",
			"[+1 Food] on [non-fresh water] tiles once [Fertilizer] is discovered",
			"[+2 Culture] for each adjacent [Oasis]"],
		"shortcutKey": "F"
	},
]
